claude_dev_cli/__init__.py
claude_dev_cli/cli.py
claude_dev_cli/commands.py
claude_dev_cli/config.py
claude_dev_cli/context.py
claude_dev_cli/core.py
claude_dev_cli/history.py
claude_dev_cli/input_sources.py
claude_dev_cli/multi_file_handler.py
claude_dev_cli/path_utils.py
claude_dev_cli/secure_storage.py
claude_dev_cli/template_manager.py
claude_dev_cli/templates.py
claude_dev_cli/toon_utils.py
claude_dev_cli/usage.py
claude_dev_cli/warp_integration.py
claude_dev_cli/workflows.py
claude_dev_cli/plugins/__init__.py
claude_dev_cli/plugins/base.py
claude_dev_cli/plugins/diff_editor/__init__.py
claude_dev_cli/plugins/diff_editor/plugin.py
claude_dev_cli/plugins/diff_editor/viewer.py
claude_dev_cli/providers/__init__.py
claude_dev_cli/providers/anthropic.py
claude_dev_cli/providers/base.py
claude_dev_cli/providers/factory.py
claude_dev_cli/providers/ollama.py
claude_dev_cli/providers/openai.py
claude_dev_cli-0.16.2.dist-info/licenses/LICENSE
claude_dev_cli-0.16.2.dist-info/METADATA
claude_dev_cli-0.16.2.dist-info/WHEEL
claude_dev_cli-0.16.2.dist-info/entry_points.txt
claude_dev_cli-0.16.2.dist-info/top_level.txt
claude_dev_cli-0.16.2.dist-info/RECORD
