Metadata-Version: 2.4
Name: claude-dev-cli
Version: 0.16.2
Summary: A powerful CLI tool for developers using Claude AI with multi-API routing, test generation, code review, and usage tracking
Author-email: Julio <thinmanj@users.noreply.github.com>
License: MIT
Project-URL: Homepage, https://github.com/thinmanj/claude-dev-cli
Project-URL: Repository, https://github.com/thinmanj/claude-dev-cli
Project-URL: Issues, https://github.com/thinmanj/claude-dev-cli/issues
Keywords: claude,ai,cli,development,testing,code-review,anthropic
Classifier: Development Status :: 4 - Beta
Classifier: Intended Audience :: Developers
Classifier: License :: OSI Approved :: MIT License
Classifier: Programming Language :: Python :: 3
Classifier: Programming Language :: Python :: 3.9
Classifier: Programming Language :: Python :: 3.10
Classifier: Programming Language :: Python :: 3.11
Classifier: Programming Language :: Python :: 3.12
Classifier: Topic :: Software Development
Classifier: Topic :: Software Development :: Code Generators
Classifier: Topic :: Software Development :: Testing
Requires-Python: >=3.9
License-File: LICENSE
Requires-Dist: anthropic>=0.18.0
Requires-Dist: click>=8.1.0
Requires-Dist: rich>=13.0.0
Requires-Dist: pydantic>=2.0.0
Requires-Dist: keyring>=24.0.0
Requires-Dist: cryptography>=41.0.0
Requires-Dist: pyyaml>=6.0.0
Requires-Dist: unidiff>=0.7.0
Provides-Extra: toon
Requires-Dist: toon-format>=0.1.0; extra == "toon"
Provides-Extra: plugins
Requires-Dist: pygments>=2.0.0; extra == "plugins"
Provides-Extra: generation
Requires-Dist: pypdf>=3.0.0; extra == "generation"
Requires-Dist: requests>=2.28.0; extra == "generation"
Requires-Dist: beautifulsoup4>=4.0.0; extra == "generation"
Provides-Extra: openai
Requires-Dist: openai>=1.0.0; extra == "openai"
Provides-Extra: ollama
Requires-Dist: requests>=2.28.0; extra == "ollama"
Provides-Extra: local
Requires-Dist: requests>=2.28.0; extra == "local"
Provides-Extra: all-providers
Requires-Dist: openai>=1.0.0; extra == "all-providers"
Requires-Dist: requests>=2.28.0; extra == "all-providers"
Provides-Extra: dev
Requires-Dist: pytest>=7.0.0; extra == "dev"
Requires-Dist: black>=23.0.0; extra == "dev"
Requires-Dist: ruff>=0.1.0; extra == "dev"
Requires-Dist: mypy>=1.0.0; extra == "dev"
Requires-Dist: toon-format>=0.1.0; extra == "dev"
Requires-Dist: pygments>=2.0.0; extra == "dev"
Requires-Dist: pypdf>=3.0.0; extra == "dev"
Requires-Dist: requests>=2.28.0; extra == "dev"
Requires-Dist: beautifulsoup4>=4.0.0; extra == "dev"
Dynamic: license-file
